neap/__init__.py
neap/report_card.py
neap-0.1.9.dist-info/METADATA
neap-0.1.9.dist-info/WHEEL
neap-0.1.9.dist-info/top_level.txt
neap-0.1.9.dist-info/RECORD
